anyakrakusuma_eot/__init__.py
anyakrakusuma_eot/cli.py
anyakrakusuma_eot/core/__init__.py
anyakrakusuma_eot/core/distributions.py
anyakrakusuma_eot/core/solver.py
anyakrakusuma_eot/io/__init__.py
anyakrakusuma_eot/io/config_manager.py
anyakrakusuma_eot/io/data_handler.py
anyakrakusuma_eot/utils/__init__.py
anyakrakusuma_eot/utils/logger.py
anyakrakusuma_eot/utils/timer.py
anyakrakusuma_eot/visualization/__init__.py
anyakrakusuma_eot/visualization/animator.py
anyakrakusuma-0.0.1.dist-info/LICENSE
anyakrakusuma-0.0.1.dist-info/METADATA
anyakrakusuma-0.0.1.dist-info/WHEEL
anyakrakusuma-0.0.1.dist-info/entry_points.txt
anyakrakusuma-0.0.1.dist-info/RECORD
