Metadata-Version: 2.3
Name: anyakrakusuma
Version: 0.0.1
Summary: 2D Schrödinger Bridge Solver via Entropic Optimal Transport with Log-Domain Sinkhorn
License: MIT
Keywords: optimal-transport,schrodinger-bridge,sinkhorn,entropic-regularization,computational-physics
Author: Sandy H. S. Herho
Requires-Python: >=3.8,<4.0
Classifier: Development Status :: 3 - Alpha
Classifier: Intended Audience :: Science/Research
Classifier: License :: OSI Approved :: MIT License
Classifier: Programming Language :: Python :: 3
Classifier: Programming Language :: Python :: 3.8
Classifier: Programming Language :: Python :: 3.9
Classifier: Programming Language :: Python :: 3.10
Classifier: Programming Language :: Python :: 3.11
Classifier: Programming Language :: Python :: 3.12
Classifier: Programming Language :: Python :: 3.13
Classifier: Topic :: Scientific/Engineering :: Mathematics
Classifier: Topic :: Scientific/Engineering :: Physics
Requires-Dist: matplotlib (>=3.3.0)
Requires-Dist: netCDF4 (>=1.5.0)
Requires-Dist: numba (>=0.53.0)
Requires-Dist: numpy (>=1.20.0)
Requires-Dist: pandas (>=1.3.0)
Requires-Dist: scipy (>=1.7.0)
Requires-Dist: tqdm (>=4.60.0)
